<?xml version="1.0" encoding="UTF-8"?>
<tv generator-info-name="WebGrab+Plus/w MDB &amp; REX Postprocess -- version  V3.1.0.0 -- Jan van Straaten" generator-info-url="http://www.webgrabplus.com">
  <channel id="HBO SIGNATURE">
    <display-name lang="es">HBO SIGNATURE</display-name>
    <url>http://www.gatotv.com</url>
  </channel>
  <channel id="HBO XTREME">
    <display-name lang="es">HBO XTREME</display-name>
    <url>http://www.gatotv.com</url>
  </channel>
  <channel id="AMC">
    <display-name lang="es">AMC</display-name>
    <url>http://www.gatotv.com</url>
  </channel>
  <channel id="CINECANAL">
    <display-name lang="es">CINECANAL</display-name>
    <url>http://www.gatotv.com</url>
  </channel>
  <channel id="CINEMAX">
    <display-name lang="es">CINEMAX</display-name>
    <url>http://www.gatotv.com</url>
  </channel>
  <channel id="CINE LATINO">
    <display-name lang="es">CINE LATINO</display-name>
    <url>http://www.gatotv.com</url>
  </channel>
  <channel id="DEPELICULA">
    <display-name lang="es">DEPELICULA</display-name>
    <url>http://www.gatotv.com</url>
  </channel>
  <channel id="DHE">
    <display-name lang="es">DHE</display-name>
    <url>http://www.gatotv.com</url>
  </channel>
  <channel id="EUROPA">
    <display-name lang="es">EUROPA</display-name>
    <url>http://www.gatotv.com</url>
  </channel>
  <channel id="EURO CHANNEL">
    <display-name lang="es">EURO CHANNEL</display-name>
    <url>http://www.gatotv.com</url>
  </channel>
  <channel id="FILMS AND ARTS">
    <display-name lang="es">FILMS AND ARTS</display-name>
    <url>http://www.gatotv.com</url>
  </channel>
  <channel id="FXM">
    <display-name lang="es">FXM</display-name>
    <url>http://www.gatotv.com</url>
  </channel>
  <channel id="GOLDEN">
    <display-name lang="es">GOLDEN</display-name>
    <url>http://www.gatotv.com</url>
  </channel>
  <channel id="GOLDEN EDGE">
    <display-name lang="es">GOLDEN EDGE</display-name>
    <url>http://www.gatotv.com</url>
  </channel>
  <channel id="GOLDEN PLUS">
    <display-name lang="es">GOLDEN PLUS</display-name>
    <url>http://www.gatotv.com</url>
  </channel>
  <channel id="GOLDEN PREMIER">
    <display-name lang="es">GOLDEN PREMIER</display-name>
    <url>http://www.gatotv.com</url>
  </channel>
  <channel id="ISAT">
    <display-name lang="es">ISAT</display-name>
    <url>http://www.gatotv.com</url>
  </channel>
  <channel id="MULTI PREMIER">
    <display-name lang="es">MULTI PREMIER</display-name>
    <url>http://www.gatotv.com</url>
  </channel>
  <programme start="20210516000200 -0500" stop="20210516020200 -0500" channel="HBO SIGNATURE">
    <title lang="es">El cuento</title>
  </programme>
  <programme start="20210516020200 -0500" stop="20210516042200 -0500" channel="HBO SIGNATURE">
    <title lang="es">Jane Fonda en cinco actos</title>
  </programme>
  <programme start="20210516042200 -0500" stop="20210516060500 -0500" channel="HBO SIGNATURE">
    <title lang="es">Borrar historial</title>
  </programme>
  <programme start="20210516060500 -0500" stop="20210516074000 -0500" channel="HBO SIGNATURE">
    <title lang="es">Stockton Siempre presente</title>
  </programme>
  <programme start="20210516074000 -0500" stop="20210516093000 -0500" channel="HBO SIGNATURE">
    <title lang="es">Paterno</title>
  </programme>
  <programme start="20210516093000 -0500" stop="20210516101500 -0500" channel="HBO SIGNATURE">
    <title lang="es">Separados en la frontera</title>
  </programme>
  <programme start="20210516101500 -0500" stop="20210516112000 -0500" channel="HBO SIGNATURE">
    <title lang="es">Mare of Easttown</title>
  </programme>
  <programme start="20210516112000 -0500" stop="20210516122500 -0500" channel="HBO SIGNATURE">
    <title lang="es">Mare of Easttown</title>
  </programme>
  <programme start="20210516122500 -0500" stop="20210516133000 -0500" channel="HBO SIGNATURE">
    <title lang="es">Mare of Easttown</title>
  </programme>
  <programme start="20210516133000 -0500" stop="20210516143400 -0500" channel="HBO SIGNATURE">
    <title lang="es">Mare of Easttown</title>
  </programme>
  <programme start="20210516143400 -0500" stop="20210516154100 -0500" channel="HBO SIGNATURE">
    <title lang="es">The Nevers</title>
  </programme>
  <programme start="20210516154100 -0500" stop="20210516164600 -0500" channel="HBO SIGNATURE">
    <title lang="es">The Nevers</title>
  </programme>
  <programme start="20210516164600 -0500" stop="20210516175000 -0500" channel="HBO SIGNATURE">
    <title lang="es">The Nevers</title>
  </programme>
  <programme start="20210516175000 -0500" stop="20210516185500 -0500" channel="HBO SIGNATURE">
    <title lang="es">The Nevers</title>
  </programme>
  <programme start="20210516185500 -0500" stop="20210516200000 -0500" channel="HBO SIGNATURE">
    <title lang="es">The Nevers</title>
  </programme>
  <programme start="20210516200000 -0500" stop="20210516222000 -0500" channel="HBO SIGNATURE">
    <title lang="es">El Mago De Las Mentiras</title>
  </programme>
  <programme start="20210516222000 -0500" stop="20210517001500 -0500" channel="HBO SIGNATURE">
    <title lang="es">O.G</title>
  </programme>
  <programme start="20210516001700 -0500" stop="20210516020300 -0500" channel="HBO XTREME">
    <title lang="es">Soldado anónimo 4</title>
  </programme>
  <programme start="20210516020300 -0500" stop="20210516040300 -0500" channel="HBO XTREME">
    <title lang="es">Fuerza antigángster</title>
  </programme>
  <programme start="20210516040300 -0500" stop="20210516060000 -0500" channel="HBO XTREME">
    <title lang="es">El Corruptor</title>
  </programme>
  <programme start="20210516060000 -0500" stop="20210516074300 -0500" channel="HBO XTREME">
    <title lang="es">Legión de Angeles</title>
  </programme>
  <programme start="20210516074300 -0500" stop="20210516104600 -0500" channel="HBO XTREME">
    <title lang="es">El señor de los anillos</title>
  </programme>
  <programme start="20210516104600 -0500" stop="20210516123500 -0500" channel="HBO XTREME">
    <title lang="es">Rápido y furioso Reto Tokio</title>
  </programme>
  <programme start="20210516123500 -0500" stop="20210516145500 -0500" channel="HBO XTREME">
    <title lang="es">RyF Hobbs &amp; Shaw</title>
  </programme>
  <programme start="20210516145500 -0500" stop="20210516165000 -0500" channel="HBO XTREME">
    <title lang="es">Bloodshot</title>
  </programme>
  <programme start="20210516165000 -0500" stop="20210516183000 -0500" channel="HBO XTREME">
    <title lang="es">Hardcore misión extrema</title>
  </programme>
  <programme start="20210516183000 -0500" stop="20210516203000 -0500" channel="HBO XTREME">
    <title lang="es">In/mortal</title>
  </programme>
  <programme start="20210516203000 -0500" stop="20210516220500 -0500" channel="HBO XTREME">
    <title lang="es">Sin Escape</title>
  </programme>
  <programme start="20210516220500 -0500" stop="20210517002500 -0500" channel="HBO XTREME">
    <title lang="es">RyF Hobbs &amp; Shaw</title>
  </programme>
  <programme start="20210516000500 -0500" stop="20210516020000 -0500" channel="AMC">
    <title lang="es">El juego de la muerte</title>
  </programme>
  <programme start="20210516020000 -0500" stop="20210516035000 -0500" channel="AMC">
    <title lang="es">Vice</title>
  </programme>
  <programme start="20210516035000 -0500" stop="20210516052000 -0500" channel="AMC">
    <title lang="es">Piraña 3D</title>
  </programme>
  <programme start="20210516052000 -0500" stop="20210516054500 -0500" channel="AMC">
    <title lang="es">Planet Action</title>
  </programme>
  <programme start="20210516054500 -0500" stop="20210516061000 -0500" channel="AMC">
    <title lang="es">Planet Action</title>
  </programme>
  <programme start="20210516061000 -0500" stop="20210516063500 -0500" channel="AMC">
    <title lang="es">Planet Action</title>
  </programme>
  <programme start="20210516063500 -0500" stop="20210516070000 -0500" channel="AMC">
    <title lang="es">Planet Action</title>
  </programme>
  <programme start="20210516070000 -0500" stop="20210516073000 -0500" channel="AMC">
    <title lang="es">Planet Action</title>
  </programme>
  <programme start="20210516073000 -0500" stop="20210516080000 -0500" channel="AMC">
    <title lang="es">Planet Action</title>
  </programme>
  <programme start="20210516080000 -0500" stop="20210516083000 -0500" channel="AMC">
    <title lang="es">Planet Action</title>
  </programme>
  <programme start="20210516083000 -0500" stop="20210516090000 -0500" channel="AMC">
    <title lang="es">Planet Action</title>
  </programme>
  <programme start="20210516090000 -0500" stop="20210516093000 -0500" channel="AMC">
    <title lang="es">Planet Action</title>
  </programme>
  <programme start="20210516093000 -0500" stop="20210516100000 -0500" channel="AMC">
    <title lang="es">Planet Action</title>
  </programme>
  <programme start="20210516100000 -0500" stop="20210516103000 -0500" channel="AMC">
    <title lang="es">Planet Action</title>
  </programme>
  <programme start="20210516103000 -0500" stop="20210516110000 -0500" channel="AMC">
    <title lang="es">Planet Action</title>
  </programme>
  <programme start="20210516110000 -0500" stop="20210516123000 -0500" channel="AMC">
    <title lang="es">7500</title>
  </programme>
  <programme start="20210516123000 -0500" stop="20210516143000 -0500" channel="AMC">
    <title lang="es">Dragon Blade</title>
  </programme>
  <programme start="20210516143000 -0500" stop="20210516162000 -0500" channel="AMC">
    <title lang="es">Centurión</title>
  </programme>
  <programme start="20210516162000 -0500" stop="20210516180000 -0500" channel="AMC">
    <title lang="es">S.W.A.T. Unidad Especial 2</title>
  </programme>
  <programme start="20210516180000 -0500" stop="20210516200500 -0500" channel="AMC">
    <title lang="es">El caza recompensas</title>
  </programme>
  <programme start="20210516200500 -0500" stop="20210516220000 -0500" channel="AMC">
    <title lang="es">Asesinos</title>
  </programme>
  <programme start="20210516220000 -0500" stop="20210517001000 -0500" channel="AMC">
    <title lang="es">RoboCop</title>
  </programme>
  <programme start="20210516020400 -0500" stop="20210516035700 -0500" channel="CINECANAL">
    <title lang="es">Asesinato en el expreso</title>
  </programme>
  <programme start="20210516035700 -0500" stop="20210516055800 -0500" channel="CINECANAL">
    <title lang="es">Cuarto de guerra</title>
  </programme>
  <programme start="20210516055800 -0500" stop="20210516072100 -0500" channel="CINECANAL">
    <title lang="es">Programación Especial</title>
  </programme>
  <programme start="20210516072100 -0500" stop="20210516084600 -0500" channel="CINECANAL">
    <title lang="es">Shopkins al estilo salvaje</title>
  </programme>
  <programme start="20210516084600 -0500" stop="20210516103400 -0500" channel="CINECANAL">
    <title lang="es">Los Pitufos 2</title>
  </programme>
  <programme start="20210516103400 -0500" stop="20210516120600 -0500" channel="CINECANAL">
    <title lang="es">Los locos Addams</title>
  </programme>
  <programme start="20210516120600 -0500" stop="20210516134100 -0500" channel="CINECANAL">
    <title lang="es">Madagascar 2</title>
  </programme>
  <programme start="20210516134100 -0500" stop="20210516151500 -0500" channel="CINECANAL">
    <title lang="es">Madagascar 3: Los fugitivos</title>
  </programme>
  <programme start="20210516151500 -0500" stop="20210516180600 -0500" channel="CINECANAL">
    <title lang="es">Blade Runner 2049</title>
  </programme>
  <programme start="20210516180600 -0500" stop="20210516200700 -0500" channel="CINECANAL">
    <title lang="es">Proyecto Géminis</title>
  </programme>
  <programme start="20210516200700 -0500" stop="20210516215900 -0500" channel="CINECANAL">
    <title lang="es">Transformers: La Era de la Extinción</title>
  </programme>
  <programme start="20210516215900 -0500" stop="20210517001000 -0500" channel="CINECANAL">
    <title lang="es">Guardianes de la Bahía</title>
  </programme>
  <programme start="20210516010500 -0500" stop="20210516030900 -0500" channel="CINEMAX">
    <title lang="es">Armados y Peligrosos (2 Guns)</title>
  </programme>
  <programme start="20210516030900 -0500" stop="20210516060000 -0500" channel="CINEMAX">
    <title lang="es">Retrato de una Dama</title>
  </programme>
  <programme start="20210516060000 -0500" stop="20210516074900 -0500" channel="CINEMAX">
    <title lang="es">Eva</title>
  </programme>
  <programme start="20210516074900 -0500" stop="20210516092700 -0500" channel="CINEMAX">
    <title lang="es">Una Coartada Perfecta</title>
  </programme>
  <programme start="20210516092700 -0500" stop="20210516113000 -0500" channel="CINEMAX">
    <title lang="es">Se busca</title>
  </programme>
  <programme start="20210516113000 -0500" stop="20210516133200 -0500" channel="CINEMAX">
    <title lang="es">Armados y Peligrosos (2 Guns)</title>
  </programme>
  <programme start="20210516133200 -0500" stop="20210516151500 -0500" channel="CINEMAX">
    <title lang="es">El rey de California</title>
  </programme>
  <programme start="20210516151500 -0500" stop="20210516171600 -0500" channel="CINEMAX">
    <title lang="es">Un traidor entre nosotros</title>
  </programme>
  <programme start="20210516171600 -0500" stop="20210516185800 -0500" channel="CINEMAX">
    <title lang="es">Fortaleza prohibida</title>
  </programme>
  <programme start="20210516185800 -0500" stop="20210516210000 -0500" channel="CINEMAX">
    <title lang="es">Armados y Peligrosos (2 Guns)</title>
  </programme>
  <programme start="20210516210000 -0500" stop="20210516230300 -0500" channel="CINEMAX">
    <title lang="es">Se busca</title>
  </programme>
  <programme start="20210516230300 -0500" stop="20210517011500 -0500" channel="CINEMAX">
    <title lang="es">El Avispón Verde</title>
  </programme>
  <programme start="20210516012500 -0500" stop="20210516030000 -0500" channel="CINE LATINO">
    <title lang="es">Las Zetas</title>
  </programme>
  <programme start="20210516030000 -0500" stop="20210516043000 -0500" channel="CINE LATINO">
    <title lang="es">Agarren al de los huevos</title>
  </programme>
  <programme start="20210516043000 -0500" stop="20210516060000 -0500" channel="CINE LATINO">
    <title lang="es">La Fiesta de los Perrones</title>
  </programme>
  <programme start="20210516060000 -0500" stop="20210516074500 -0500" channel="CINE LATINO">
    <title lang="es">Sanky Panky 3</title>
  </programme>
  <programme start="20210516074500 -0500" stop="20210516090500 -0500" channel="CINE LATINO">
    <title lang="es">12 rounds</title>
  </programme>
  <programme start="20210516090500 -0500" stop="20210516110000 -0500" channel="CINE LATINO">
    <title lang="es">La Diosa del Mar</title>
  </programme>
  <programme start="20210516110000 -0500" stop="20210516124500 -0500" channel="CINE LATINO">
    <title lang="es">El Rumor de las Piedras</title>
  </programme>
  <programme start="20210516124500 -0500" stop="20210516142500 -0500" channel="CINE LATINO">
    <title lang="es">Los Ángeles</title>
  </programme>
  <programme start="20210516142500 -0500" stop="20210516161500 -0500" channel="CINE LATINO">
    <title lang="es">Historias del canal</title>
  </programme>
  <programme start="20210516161500 -0500" stop="20210516174500 -0500" channel="CINE LATINO">
    <title lang="es">Lecciones de Vida</title>
  </programme>
  <programme start="20210516174500 -0500" stop="20210516190000 -0500" channel="CINE LATINO">
    <title lang="es">Septiembre, Un Llanto en Silencio</title>
  </programme>
  <programme start="20210516190000 -0500" stop="20210516193000 -0500" channel="CINE LATINO">
    <title lang="es">Desde nuestro muxu'x</title>
  </programme>
  <programme start="20210516193000 -0500" stop="20210516210000 -0500" channel="CINE LATINO">
    <title lang="es">Oveja negra</title>
  </programme>
  <programme start="20210516210000 -0500" stop="20210516221500 -0500" channel="CINE LATINO">
    <title lang="es">Septiembre, Un Llanto en Silencio</title>
  </programme>
  <programme start="20210516221500 -0500" stop="20210516235000 -0500" channel="CINE LATINO">
    <title lang="es">No quiero estar sin ti</title>
  </programme>
  <programme start="20210516235000 -0500" stop="20210517012500 -0500" channel="CINE LATINO">
    <title lang="es">Como dos gotas de agua</title>
  </programme>
  <programme start="20210516012100 -0500" stop="20210516030900 -0500" channel="DEPELICULA">
    <title lang="es">El moro de cumpas</title>
  </programme>
  <programme start="20210516030900 -0500" stop="20210516043500 -0500" channel="DEPELICULA">
    <title lang="es">El pantano de las ánimas</title>
  </programme>
  <programme start="20210516043500 -0500" stop="20210516060000 -0500" channel="DEPELICULA">
    <title lang="es">Subida al cielo</title>
  </programme>
  <programme start="20210516060000 -0500" stop="20210516075800 -0500" channel="DEPELICULA">
    <title lang="es">Jalisco nunca pierde</title>
  </programme>
  <programme start="20210516075800 -0500" stop="20210516093500 -0500" channel="DEPELICULA">
    <title lang="es">Chabelo y Pepito detectives</title>
  </programme>
  <programme start="20210516093500 -0500" stop="20210516111700 -0500" channel="DEPELICULA">
    <title lang="es">Yo el aventurero</title>
  </programme>
  <programme start="20210516111700 -0500" stop="20210516124000 -0500" channel="DEPELICULA">
    <title lang="es">El grito de la muerte</title>
  </programme>
  <programme start="20210516124000 -0500" stop="20210516141200 -0500" channel="DEPELICULA">
    <title lang="es">Los olvidados</title>
  </programme>
  <programme start="20210516141200 -0500" stop="20210516162200 -0500" channel="DEPELICULA">
    <title lang="es">Mi esposa y la otra</title>
  </programme>
  <programme start="20210516162200 -0500" stop="20210516181300 -0500" channel="DEPELICULA">
    <title lang="es">María Candelaria</title>
  </programme>
  <programme start="20210516181300 -0500" stop="20210516201900 -0500" channel="DEPELICULA">
    <title lang="es">El analfabeto</title>
  </programme>
  <programme start="20210516201900 -0500" stop="20210516214100 -0500" channel="DEPELICULA">
    <title lang="es">El grito de la muerte</title>
  </programme>
  <programme start="20210516214100 -0500" stop="20210516232900 -0500" channel="DEPELICULA">
    <title lang="es">Siempre en domingo</title>
  </programme>
  <programme start="20210516232900 -0500" stop="20210517011600 -0500" channel="DEPELICULA">
    <title lang="es">Bajas pasiones</title>
  </programme>
  <programme start="20210516010000 -0500" stop="20210516022500 -0500" channel="DHE">
    <title lang="es">Maníaco</title>
  </programme>
  <programme start="20210516022500 -0500" stop="20210516041500 -0500" channel="DHE">
    <title lang="es">Fugitivo</title>
  </programme>
  <programme start="20210516041500 -0500" stop="20210516060000 -0500" channel="DHE">
    <title lang="es">El Principito</title>
  </programme>
  <programme start="20210516060000 -0500" stop="20210516072500 -0500" channel="DHE">
    <title lang="es">Ploey</title>
  </programme>
  <programme start="20210516072500 -0500" stop="20210516091500 -0500" channel="DHE">
    <title lang="es">Janie Jones</title>
  </programme>
  <programme start="20210516091500 -0500" stop="20210516110000 -0500" channel="DHE">
    <title lang="es">Tal vez es para siempre</title>
  </programme>
  <programme start="20210516110000 -0500" stop="20210516124000 -0500" channel="DHE">
    <title lang="es">Furia de centuriones</title>
  </programme>
  <programme start="20210516124000 -0500" stop="20210516141000 -0500" channel="DHE">
    <title lang="es">Acorralados</title>
  </programme>
  <programme start="20210516141000 -0500" stop="20210516155000 -0500" channel="DHE">
    <title lang="es">En busca del asesino</title>
  </programme>
  <programme start="20210516155000 -0500" stop="20210516174500 -0500" channel="DHE">
    <title lang="es">Albert Nobbs</title>
  </programme>
  <programme start="20210516174500 -0500" stop="20210516194000 -0500" channel="DHE">
    <title lang="es">Triste San Valentín</title>
  </programme>
  <programme start="20210516194000 -0500" stop="20210516201000 -0500" channel="DHE">
    <title lang="es">El Lugar Bueno</title>
  </programme>
  <programme start="20210516201000 -0500" stop="20210516222500 -0500" channel="DHE">
    <title lang="es">Diré tu nombre</title>
  </programme>
  <programme start="20210516222500 -0500" stop="20210517000500 -0500" channel="DHE">
    <title lang="es">Los Curados</title>
  </programme>
  <programme start="20210516000500 -0500" stop="20210516020500 -0500" channel="EUROPA">
    <title lang="es">Tal vez es para siempre</title>
  </programme>
  <programme start="20210516020500 -0500" stop="20210516041000 -0500" channel="EUROPA">
    <title lang="es">Una historia equivocada</title>
  </programme>
  <programme start="20210516041000 -0500" stop="20210516060000 -0500" channel="EUROPA">
    <title lang="es">Había una vez en Salzburgo</title>
  </programme>
  <programme start="20210516060000 -0500" stop="20210516080500 -0500" channel="EUROPA">
    <title lang="es">Montalbano</title>
  </programme>
  <programme start="20210516080500 -0500" stop="20210516094500 -0500" channel="EUROPA">
    <title lang="es">Cuestión de karma</title>
  </programme>
  <programme start="20210516094500 -0500" stop="20210516114500 -0500" channel="EUROPA">
    <title lang="es">Tal vez es para siempre</title>
  </programme>
  <programme start="20210516114500 -0500" stop="20210516133000 -0500" channel="EUROPA">
    <title lang="es">Había una vez en Salzburgo</title>
  </programme>
  <programme start="20210516133000 -0500" stop="20210516154500 -0500" channel="EUROPA">
    <title lang="es">Contra el viento del Norte</title>
  </programme>
  <programme start="20210516154500 -0500" stop="20210516175500 -0500" channel="EUROPA">
    <title lang="es">Montalbano</title>
  </programme>
  <programme start="20210516175500 -0500" stop="20210516200000 -0500" channel="EUROPA">
    <title lang="es">Montalbano</title>
  </programme>
  <programme start="20210516200000 -0500" stop="20210516222500 -0500" channel="EUROPA">
    <title lang="es">Grandes esperanzas</title>
  </programme>
  <programme start="20210516222500 -0500" stop="20210516230000 -0500" channel="EUROPA">
    <title lang="es">Hechizada</title>
  </programme>
  <programme start="20210516230000 -0500" stop="20210517010500 -0500" channel="EUROPA">
    <title lang="es">Montalbano</title>
  </programme>
  <programme start="20210516003000 -0500" stop="20210516013000 -0500" channel="EURO CHANNEL">
    <title lang="es">La furia</title>
  </programme>
  <programme start="20210516013000 -0500" stop="20210516023000 -0500" channel="EURO CHANNEL">
    <title lang="es">La furia</title>
  </programme>
  <programme start="20210516023000 -0500" stop="20210516040000 -0500" channel="EURO CHANNEL">
    <title lang="es">El silencio de la muerte</title>
  </programme>
  <programme start="20210516040000 -0500" stop="20210516055500 -0500" channel="EURO CHANNEL">
    <title lang="es">Fuego en el corazón</title>
  </programme>
  <programme start="20210516055500 -0500" stop="20210516075000 -0500" channel="EURO CHANNEL">
    <title lang="es">Silencio roto</title>
  </programme>
  <programme start="20210516075000 -0500" stop="20210516085000 -0500" channel="EURO CHANNEL">
    <title lang="es">La furia</title>
  </programme>
  <programme start="20210516085000 -0500" stop="20210516095000 -0500" channel="EURO CHANNEL">
    <title lang="es">La furia</title>
  </programme>
  <programme start="20210516095000 -0500" stop="20210516114000 -0500" channel="EURO CHANNEL">
    <title lang="es">Bésame mucho</title>
  </programme>
  <programme start="20210516114000 -0500" stop="20210516133000 -0500" channel="EURO CHANNEL">
    <title lang="es">Bésame mucho</title>
  </programme>
  <programme start="20210516133000 -0500" stop="20210516143000 -0500" channel="EURO CHANNEL">
    <title lang="es">Cuando cae la noche</title>
  </programme>
  <programme start="20210516143000 -0500" stop="20210516153000 -0500" channel="EURO CHANNEL">
    <title lang="es">Cuando cae la noche</title>
  </programme>
  <programme start="20210516153000 -0500" stop="20210516162000 -0500" channel="EURO CHANNEL">
    <title lang="es">Salvación</title>
  </programme>
  <programme start="20210516162000 -0500" stop="20210516171000 -0500" channel="EURO CHANNEL">
    <title lang="es">Salvación</title>
  </programme>
  <programme start="20210516171000 -0500" stop="20210516190000 -0500" channel="EURO CHANNEL">
    <title lang="es">Fuego en el corazón</title>
  </programme>
  <programme start="20210516190000 -0500" stop="20210516194500 -0500" channel="EURO CHANNEL">
    <title lang="es">Secreto mortal - Parte 1</title>
  </programme>
  <programme start="20210516194500 -0500" stop="20210516203500 -0500" channel="EURO CHANNEL">
    <title lang="es">Secreto mortal - Parte 2</title>
  </programme>
  <programme start="20210516203500 -0500" stop="20210516220500 -0500" channel="EURO CHANNEL">
    <title lang="es">El secreto del oso</title>
  </programme>
  <programme start="20210516220500 -0500" stop="20210516233500 -0500" channel="EURO CHANNEL">
    <title lang="es">Pasion mortal</title>
  </programme>
  <programme start="20210516233500 -0500" stop="20210517010500 -0500" channel="EURO CHANNEL">
    <title lang="es">Besos escondidos</title>
  </programme>
  <programme start="20210516020500 -0500" stop="20210516040000 -0500" channel="FILMS AND ARTS">
    <title lang="es">Fausto</title>
  </programme>
  <programme start="20210516040000 -0500" stop="20210516054500 -0500" channel="FILMS AND ARTS">
    <title lang="es">Vera</title>
  </programme>
  <programme start="20210516054500 -0500" stop="20210516060000 -0500" channel="FILMS AND ARTS">
    <title lang="es">Cuentos de 10 minutos</title>
  </programme>
  <programme start="20210516060000 -0500" stop="20210516063000 -0500" channel="FILMS AND ARTS">
    <title lang="es">Photo</title>
  </programme>
  <programme start="20210516063000 -0500" stop="20210516073000 -0500" channel="FILMS AND ARTS">
    <title lang="es">Graham Norton Show</title>
  </programme>
  <programme start="20210516073000 -0500" stop="20210516091500 -0500" channel="FILMS AND ARTS">
    <title lang="es">Fausto</title>
  </programme>
  <programme start="20210516091500 -0500" stop="20210516110000 -0500" channel="FILMS AND ARTS">
    <title lang="es">Persona</title>
  </programme>
  <programme start="20210516110000 -0500" stop="20210516120000 -0500" channel="FILMS AND ARTS">
    <title lang="es">Graham Norton Show</title>
  </programme>
  <programme start="20210516120000 -0500" stop="20210516134500 -0500" channel="FILMS AND ARTS">
    <title lang="es">Vera</title>
  </programme>
  <programme start="20210516134500 -0500" stop="20210516141800 -0500" channel="FILMS AND ARTS">
    <title lang="es">Photo</title>
  </programme>
  <programme start="20210516141800 -0500" stop="20210516160000 -0500" channel="FILMS AND ARTS">
    <title lang="es">Las chicas de la banda</title>
  </programme>
  <programme start="20210516160000 -0500" stop="20210516181500 -0500" channel="FILMS AND ARTS">
    <title lang="es">Átame</title>
  </programme>
  <programme start="20210516181500 -0500" stop="20210516183000 -0500" channel="FILMS AND ARTS">
    <title lang="es">Cuentos de 10 minutos</title>
  </programme>
  <programme start="20210516183000 -0500" stop="20210516200000 -0500" channel="FILMS AND ARTS">
    <title lang="es">Kullervo</title>
  </programme>
  <programme start="20210516200000 -0500" stop="20210516210000 -0500" channel="FILMS AND ARTS">
    <title lang="es">Agent Hamilton</title>
  </programme>
  <programme start="20210516210000 -0500" stop="20210516220000 -0500" channel="FILMS AND ARTS">
    <title lang="es">Babylon Berlin</title>
  </programme>
  <programme start="20210516220000 -0500" stop="20210517000000 -0500" channel="FILMS AND ARTS">
    <title lang="es">Analizando a Philip</title>
  </programme>
  <programme start="20210516003200 -0500" stop="20210516023400 -0500" channel="FXM">
    <title lang="es">Vuelo a la gloria</title>
  </programme>
  <programme start="20210516023400 -0500" stop="20210516044500 -0500" channel="FXM">
    <title lang="es">Cumbres borrascosas</title>
  </programme>
  <programme start="20210516044500 -0500" stop="20210516062300 -0500" channel="FXM">
    <title lang="es">Desde México con amor</title>
  </programme>
  <programme start="20210516062300 -0500" stop="20210516070000 -0500" channel="FXM">
    <title lang="es">Programación Especial</title>
  </programme>
  <programme start="20210516070000 -0500" stop="20210516094700 -0500" channel="FXM">
    <title lang="es">La tierra de sombras</title>
  </programme>
  <programme start="20210516094700 -0500" stop="20210516115600 -0500" channel="FXM">
    <title lang="es">Gente como uno</title>
  </programme>
  <programme start="20210516115600 -0500" stop="20210516140800 -0500" channel="FXM">
    <title lang="es">Indiana Jones y el reino</title>
  </programme>
  <programme start="20210516140800 -0500" stop="20210516165000 -0500" channel="FXM">
    <title lang="es">El Sustituto (Changeling)</title>
  </programme>
  <programme start="20210516165000 -0500" stop="20210516191500 -0500" channel="FXM">
    <title lang="es">Códigos de guerra</title>
  </programme>
  <programme start="20210516191500 -0500" stop="20210516210000 -0500" channel="FXM">
    <title lang="es">Nacho libre</title>
  </programme>
  <programme start="20210516210000 -0500" stop="20210516230700 -0500" channel="FXM">
    <title lang="es">Máxima Velocidad</title>
  </programme>
  <programme start="20210516230700 -0500" stop="20210517011100 -0500" channel="FXM">
    <title lang="es">RoboCop</title>
  </programme>
  <programme start="20210516005800 -0500" stop="20210516024700 -0500" channel="GOLDEN">
    <title lang="es">Mother Exchange</title>
  </programme>
  <programme start="20210516024700 -0500" stop="20210516044000 -0500" channel="GOLDEN">
    <title lang="es">No Manches Frida 2</title>
  </programme>
  <programme start="20210516044000 -0500" stop="20210516060500 -0500" channel="GOLDEN">
    <title lang="es">Un Caballo Llamado Elefante</title>
  </programme>
  <programme start="20210516060500 -0500" stop="20210516073700 -0500" channel="GOLDEN">
    <title lang="es">Sammy en el pasaje secreto</title>
  </programme>
  <programme start="20210516073700 -0500" stop="20210516091900 -0500" channel="GOLDEN">
    <title lang="es">Mortadelo y Filemón</title>
  </programme>
  <programme start="20210516091900 -0500" stop="20210516110000 -0500" channel="GOLDEN">
    <title lang="es">Babe El Puerquito va a</title>
  </programme>
  <programme start="20210516110000 -0500" stop="20210516130200 -0500" channel="GOLDEN">
    <title lang="es">El cazarecompensas</title>
  </programme>
  <programme start="20210516130200 -0500" stop="20210516151200 -0500" channel="GOLDEN">
    <title lang="es">Hitch Especialista en</title>
  </programme>
  <programme start="20210516151200 -0500" stop="20210516171600 -0500" channel="GOLDEN">
    <title lang="es">No me quites a mi novio</title>
  </programme>
  <programme start="20210516171600 -0500" stop="20210516190000 -0500" channel="GOLDEN">
    <title lang="es">Como si fuera la primera vez</title>
  </programme>
  <programme start="20210516190000 -0500" stop="20210516210000 -0500" channel="GOLDEN">
    <title lang="es">¿Y dónde están las rubias</title>
  </programme>
  <programme start="20210516210000 -0500" stop="20210516224200 -0500" channel="GOLDEN">
    <title lang="es">Al Diablo con el amor</title>
  </programme>
  <programme start="20210516224200 -0500" stop="20210517003900 -0500" channel="GOLDEN">
    <title lang="es">Una cita en el parque</title>
  </programme>
  <programme start="20210516002400 -0500" stop="20210516015200 -0500" channel="GOLDEN EDGE">
    <title lang="es">Rec</title>
  </programme>
  <programme start="20210516015200 -0500" stop="20210516032400 -0500" channel="GOLDEN EDGE">
    <title lang="es">American curious</title>
  </programme>
  <programme start="20210516032400 -0500" stop="20210516045200 -0500" channel="GOLDEN EDGE">
    <title lang="es">Abel</title>
  </programme>
  <programme start="20210516045200 -0500" stop="20210516063900 -0500" channel="GOLDEN EDGE">
    <title lang="es">Ladrones</title>
  </programme>
  <programme start="20210516063900 -0500" stop="20210516082900 -0500" channel="GOLDEN EDGE">
    <title lang="es">Arthur 3</title>
  </programme>
  <programme start="20210516082900 -0500" stop="20210516101600 -0500" channel="GOLDEN EDGE">
    <title lang="es">Zapatero a tus zapatos</title>
  </programme>
  <programme start="20210516101600 -0500" stop="20210516122300 -0500" channel="GOLDEN EDGE">
    <title lang="es">Olimpo bajo fuego</title>
  </programme>
  <programme start="20210516122300 -0500" stop="20210516143000 -0500" channel="GOLDEN EDGE">
    <title lang="es">The karate kid 3</title>
  </programme>
  <programme start="20210516143000 -0500" stop="20210516163800 -0500" channel="GOLDEN EDGE">
    <title lang="es">Sin Escape Alguno</title>
  </programme>
  <programme start="20210516163800 -0500" stop="20210516182000 -0500" channel="GOLDEN EDGE">
    <title lang="es">Brusco despertar</title>
  </programme>
  <programme start="20210516182000 -0500" stop="20210516203000 -0500" channel="GOLDEN EDGE">
    <title lang="es">Latin Lover</title>
  </programme>
  <programme start="20210516203000 -0500" stop="20210516220000 -0500" channel="GOLDEN EDGE">
    <title lang="es">El Animal</title>
  </programme>
  <programme start="20210516220000 -0500" stop="20210516234300 -0500" channel="GOLDEN EDGE">
    <title lang="es">Héroe de Centro Comercial 2</title>
  </programme>
  <programme start="20210516234300 -0500" stop="20210517020100 -0500" channel="GOLDEN EDGE">
    <title lang="es">Bajos instintos</title>
  </programme>
  <programme start="20210516001700 -0500" stop="20210516015800 -0500" channel="GOLDEN PLUS">
    <title lang="es">Suave patria</title>
  </programme>
  <programme start="20210516015800 -0500" stop="20210516033800 -0500" channel="GOLDEN PLUS">
    <title lang="es">Una vida mejor</title>
  </programme>
  <programme start="20210516033800 -0500" stop="20210516051300 -0500" channel="GOLDEN PLUS">
    <title lang="es">Busco Novio para mi Mujer</title>
  </programme>
  <programme start="20210516051300 -0500" stop="20210516064000 -0500" channel="GOLDEN PLUS">
    <title lang="es">La leyenda de las momias de Guanajuato</title>
  </programme>
  <programme start="20210516064000 -0500" stop="20210516080600 -0500" channel="GOLDEN PLUS">
    <title lang="es">La Leyenda del Chupacabras</title>
  </programme>
  <programme start="20210516080600 -0500" stop="20210516092800 -0500" channel="GOLDEN PLUS">
    <title lang="es">9</title>
  </programme>
  <programme start="20210516092800 -0500" stop="20210516111400 -0500" channel="GOLDEN PLUS">
    <title lang="es">Eres mi pasión</title>
  </programme>
  <programme start="20210516111400 -0500" stop="20210516124500 -0500" channel="GOLDEN PLUS">
    <title lang="es">Tuya, Mia... Te la Apuesto</title>
  </programme>
  <programme start="20210516124500 -0500" stop="20210516142500 -0500" channel="GOLDEN PLUS">
    <title lang="es">Ladrones</title>
  </programme>
  <programme start="20210516142500 -0500" stop="20210516160000 -0500" channel="GOLDEN PLUS">
    <title lang="es">Busco Novio para mi Mujer</title>
  </programme>
  <programme start="20210516160000 -0500" stop="20210516181100 -0500" channel="GOLDEN PLUS">
    <title lang="es">El Golpe</title>
  </programme>
  <programme start="20210516181100 -0500" stop="20210516200600 -0500" channel="GOLDEN PLUS">
    <title lang="es">No me quites a mi novio</title>
  </programme>
  <programme start="20210516200600 -0500" stop="20210516220000 -0500" channel="GOLDEN PLUS">
    <title lang="es">Step Up: todos a bailar</title>
  </programme>
  <programme start="20210516220000 -0500" stop="20210516233800 -0500" channel="GOLDEN PLUS">
    <title lang="es">Bhopal: Una Oración Por La Lluvia</title>
  </programme>
  <programme start="20210516233800 -0500" stop="20210517000500 -0500" channel="GOLDEN PLUS">
    <title lang="es">Erotic Stories</title>
  </programme>
  <programme start="20210516011500 -0500" stop="20210516025200 -0500" channel="GOLDEN PREMIER">
    <title lang="es">The Babysitter</title>
  </programme>
  <programme start="20210516025200 -0500" stop="20210516042500 -0500" channel="GOLDEN PREMIER">
    <title lang="es">Cuenta regresiva</title>
  </programme>
  <programme start="20210516042500 -0500" stop="20210516053800 -0500" channel="GOLDEN PREMIER">
    <title lang="es">Más allá de mí</title>
  </programme>
  <programme start="20210516053800 -0500" stop="20210516070600 -0500" channel="GOLDEN PREMIER">
    <title lang="es">Todos los perros van al cielo</title>
  </programme>
  <programme start="20210516070600 -0500" stop="20210516083800 -0500" channel="GOLDEN PREMIER">
    <title lang="es">Bailarina</title>
  </programme>
  <programme start="20210516083800 -0500" stop="20210516102300 -0500" channel="GOLDEN PREMIER">
    <title lang="es">Boo! A madea Halloween</title>
  </programme>
  <programme start="20210516102300 -0500" stop="20210516115100 -0500" channel="GOLDEN PREMIER">
    <title lang="es">Todos los perros van al cielo</title>
  </programme>
  <programme start="20210516115100 -0500" stop="20210516131900 -0500" channel="GOLDEN PREMIER">
    <title lang="es">Locos Por Las Nueces</title>
  </programme>
  <programme start="20210516131900 -0500" stop="20210516145800 -0500" channel="GOLDEN PREMIER">
    <title lang="es">Paddington</title>
  </programme>
  <programme start="20210516145800 -0500" stop="20210516163300 -0500" channel="GOLDEN PREMIER">
    <title lang="es">Mortadelo y Filemón</title>
  </programme>
  <programme start="20210516163300 -0500" stop="20210516182200 -0500" channel="GOLDEN PREMIER">
    <title lang="es">El gran pequeño</title>
  </programme>
  <programme start="20210516182200 -0500" stop="20210516201000 -0500" channel="GOLDEN PREMIER">
    <title lang="es">All Is Lost</title>
  </programme>
  <programme start="20210516201000 -0500" stop="20210516220000 -0500" channel="GOLDEN PREMIER">
    <title lang="es">Una pareja dispareja</title>
  </programme>
  <programme start="20210516220000 -0500" stop="20210516234300 -0500" channel="GOLDEN PREMIER">
    <title lang="es">Un pequeño cambio</title>
  </programme>
  <programme start="20210516234300 -0500" stop="20210517013900 -0500" channel="GOLDEN PREMIER">
    <title lang="es">El Juego de Ender</title>
  </programme>
  <programme start="20210516013900 -0500" stop="20210516025900 -0500" channel="ISAT">
    <title lang="es">Upa! 2</title>
  </programme>
  <programme start="20210516025900 -0500" stop="20210516041500 -0500" channel="ISAT">
    <title lang="es">Here Kitty Kitty</title>
  </programme>
  <programme start="20210516041500 -0500" stop="20210516065300 -0500" channel="ISAT">
    <title lang="es">Cuentos de terror</title>
  </programme>
  <programme start="20210516065300 -0500" stop="20210516081600 -0500" channel="ISAT">
    <title lang="es">El Almafuerte</title>
  </programme>
  <programme start="20210516081600 -0500" stop="20210516093700 -0500" channel="ISAT">
    <title lang="es">La parte por el todo</title>
  </programme>
  <programme start="20210516093700 -0500" stop="20210516111400 -0500" channel="ISAT">
    <title lang="es">Hello, My Name is Doris</title>
  </programme>
  <programme start="20210516111400 -0500" stop="20210516113900 -0500" channel="ISAT">
    <title lang="es">Luchadoras Hacia la conquista</title>
  </programme>
  <programme start="20210516113900 -0500" stop="20210516133200 -0500" channel="ISAT">
    <title lang="es">The end of the tour</title>
  </programme>
  <programme start="20210516133200 -0500" stop="20210516151700 -0500" channel="ISAT">
    <title lang="es">Un buen dia</title>
  </programme>
  <programme start="20210516151700 -0500" stop="20210516164400 -0500" channel="ISAT">
    <title lang="es">Los Índalos</title>
  </programme>
  <programme start="20210516164400 -0500" stop="20210516181000 -0500" channel="ISAT">
    <title lang="es">Pichuco</title>
  </programme>
  <programme start="20210516181000 -0500" stop="20210516194800 -0500" channel="ISAT">
    <title lang="es">Brigsby Bear</title>
  </programme>
  <programme start="20210516194800 -0500" stop="20210516220000 -0500" channel="ISAT">
    <title lang="es">Spotlight</title>
  </programme>
  <programme start="20210516220000 -0500" stop="20210516234800 -0500" channel="ISAT">
    <title lang="es">Miles Ahead</title>
  </programme>
  <programme start="20210516234800 -0500" stop="20210517012000 -0500" channel="ISAT">
    <title lang="es">50 Chuseok</title>
  </programme>
  <programme start="20210516005500 -0500" stop="20210516023000 -0500" channel="MULTI PREMIER">
    <title lang="es">Diario erótico</title>
  </programme>
  <programme start="20210516023000 -0500" stop="20210516043000 -0500" channel="MULTI PREMIER">
    <title lang="es">Damiselas en problemas</title>
  </programme>
  <programme start="20210516043000 -0500" stop="20210516050000 -0500" channel="MULTI PREMIER">
    <title lang="es">Paid Programming</title>
  </programme>
  <programme start="20210516050000 -0500" stop="20210516053000 -0500" channel="MULTI PREMIER">
    <title lang="es">Paid Programming</title>
  </programme>
  <programme start="20210516053000 -0500" stop="20210516060000 -0500" channel="MULTI PREMIER">
    <title lang="es">Paid Programming</title>
  </programme>
  <programme start="20210516060000 -0500" stop="20210516075000 -0500" channel="MULTI PREMIER">
    <title lang="es">La ventana secreta</title>
  </programme>
  <programme start="20210516075000 -0500" stop="20210516094000 -0500" channel="MULTI PREMIER">
    <title lang="es">Estrictamente para salón de baile</title>
  </programme>
  <programme start="20210516094000 -0500" stop="20210516113500 -0500" channel="MULTI PREMIER">
    <title lang="es">Secretos mortales</title>
  </programme>
  <programme start="20210516113500 -0500" stop="20210516114000 -0500" channel="MULTI PREMIER">
    <title lang="es">Paid Programming</title>
  </programme>
  <programme start="20210516114000 -0500" stop="20210516133500 -0500" channel="MULTI PREMIER">
    <title lang="es">El hombre perfecto</title>
  </programme>
  <programme start="20210516133500 -0500" stop="20210516153000 -0500" channel="MULTI PREMIER">
    <title lang="es">La ventana secreta</title>
  </programme>
  <programme start="20210516153000 -0500" stop="20210516172000 -0500" channel="MULTI PREMIER">
    <title lang="es">Estrictamente para salón de baile</title>
  </programme>
  <programme start="20210516172000 -0500" stop="20210516191500 -0500" channel="MULTI PREMIER">
    <title lang="es">Secretos mortales</title>
  </programme>
  <programme start="20210516191500 -0500" stop="20210516210000 -0500" channel="MULTI PREMIER">
    <title lang="es">La píldora amarga</title>
  </programme>
  <programme start="20210516210000 -0500" stop="20210516225000 -0500" channel="MULTI PREMIER">
    <title lang="es">Manos milagrosas</title>
  </programme>
  <programme start="20210516225000 -0500" stop="20210517004000 -0500" channel="MULTI PREMIER">
    <title lang="es">Manos milagrosas</title>
  </programme>
</tv>